{
  "items": [
    {
      "id": "health_potion",
      "name": "Health Potion",
      "color": "#d04848",
      "stackable": true,
      "maxStack": 20,
      "description": "Restores 25 HP. Use from the hotbar.",
      "type": "consumable",
      "consumable": { "healHp": 25 },
      "value": 30
    },
    {
      "id": "slime_goo",
      "name": "Slime Goo",
      "color": "#7ad06b",
      "stackable": true,
      "maxStack": 50,
      "description": "Sticky residue from a vanquished slime.",
      "type": "resource",
      "value": 3
    },
    {
      "id": "rope",
      "name": "Rope",
      "color": "#c8a36a",
      "stackable": true,
      "maxStack": 50,
      "description": "A coil of sturdy hemp rope.",
      "type": "resource",
      "value": 2
    },
    {
      "id": "plank",
      "name": "Plank",
      "color": "#8b5a2b",
      "stackable": true,
      "maxStack": 50,
      "description": "A length of weathered timber.",
      "type": "resource",
      "value": 3
    },
    {
      "id": "fish",
      "name": "Fish",
      "color": "#6bb7d6",
      "stackable": true,
      "maxStack": 20,
      "description": "Fresh from the sea.",
      "type": "consumable",
      "value": 4
    },
    {
      "id": "coin",
      "name": "Gold Coin",
      "color": "#e5c14a",
      "stackable": true,
      "maxStack": 1000,
      "description": "A doubloon bearing a weathered crest.",
      "type": "resource",
      "value": 1
    },
    {
      "id": "compass",
      "name": "Compass",
      "color": "#b4c3d4",
      "stackable": false,
      "maxStack": 1,
      "description": "Points true north, mostly.",
      "type": "tool",
      "value": 50
    },
    {
      "id": "tricorn",
      "name": "Tricorn Hat",
      "color": "#2a2030",
      "stackable": false,
      "maxStack": 1,
      "description": "Battered three-cornered hat. Makes you look the part.",
      "type": "armor",
      "slot": "head",
      "stats": { "defense": 1 },
      "visualLayer": { "layer": "accessory", "variant": "farmer-hat" },
      "value": 40
    },
    {
      "id": "sailors_coat",
      "name": "Sailor's Coat",
      "color": "#345c7a",
      "stackable": false,
      "maxStack": 1,
      "description": "Salt-stained wool. Warmer than it looks.",
      "type": "armor",
      "slot": "body",
      "stats": { "maxHp": 5, "defense": 2 },
      "visualLayer": { "layer": "chest", "variant": "royal-blue" },
      "value": 120
    },
    {
      "id": "leather_boots",
      "name": "Leather Boots",
      "color": "#6b4a2a",
      "stackable": false,
      "maxStack": 1,
      "description": "Sturdy boots with good tread for wet decks.",
      "type": "armor",
      "slot": "legs",
      "stats": { "moveSpeed": 12 },
      "visualLayer": { "layer": "feet", "variant": "black" },
      "value": 60
    },
    {
      "id": "cutlass",
      "name": "Cutlass",
      "color": "#c0c0c0",
      "stackable": false,
      "maxStack": 1,
      "description": "A curved sword, well-balanced for close quarters.",
      "type": "weapon",
      "slot": "mainHand",
      "stats": { "attack": 5 },
      "visualLayer": { "layer": "tool", "variant": "iron-sword" },
      "value": 200
    },
    {
      "id": "sword",
      "name": "Sword",
      "color": "#c0c0c0",
      "stackable": false,
      "maxStack": 1,
      "description": "A plain iron sword. Equip, then press Q to swing.",
      "type": "weapon",
      "slot": "mainHand",
      "stats": { "attack": 3 },
      "visualLayer": { "layer": "tool", "variant": "iron-sword" },
      "value": 3
    },
    {
      "id": "bow",
      "name": "Shortbow",
      "color": "#8a6a3d",
      "stackable": false,
      "maxStack": 1,
      "description": "A simple shortbow. Equip, then left-click to fire arrows.",
      "type": "weapon",
      "slot": "mainHand",
      "skill": "ranger",
      "stats": { "attack": 2 },
      "ranged": {
        "rangePx": 320,
        "projectileSpeedPx": 480,
        "damage": 2,
        "projectile": "arrow",
        "cooldownMs": 500
      },
      "visualLayer": { "layer": "tool", "variant": "wooden-bow" },
      "value": 3
    },
    {
      "id": "arrow",
      "name": "Arrow",
      "color": "#a88050",
      "stackable": true,
      "maxStack": 99,
      "description": "Ammunition for a bow.",
      "type": "ammo",
      "value": 1,
      "bundle": { "quantity": 15, "buyPrice": 5, "sellPrice": 2 }
    },
    {
      "id": "pickaxe",
      "name": "Pickaxe",
      "color": "#8a6a3d",
      "stackable": false,
      "maxStack": 1,
      "description": "A sturdy pickaxe. Equip, then press Q to mine.",
      "type": "tool",
      "slot": "mainHand",
      "visualLayer": { "layer": "tool", "variant": "iron-pickaxe" },
      "value": 3
    },
    {
      "id": "axe",
      "name": "Axe",
      "color": "#7a5a2a",
      "stackable": false,
      "maxStack": 1,
      "description": "A felling axe. Equip, then press Q to chop trees.",
      "type": "tool",
      "slot": "mainHand",
      "skill": "lumberjack",
      "visualLayer": { "layer": "tool", "variant": "iron-axe" },
      "value": 3
    },
    {
      "id": "fishing_rod",
      "name": "Fishing Rod",
      "color": "#a07050",
      "stackable": false,
      "maxStack": 1,
      "description": "A bamboo rod and line. Equip, then press Q at a fishing spot.",
      "type": "tool",
      "slot": "mainHand",
      "skill": "fishing",
      "visualLayer": { "layer": "tool", "variant": "wooden-fishing-rod" },
      "value": 3
    },
    {
      "id": "hopeite_ore",
      "name": "Hopeite Ore",
      "color": "#b07a3a",
      "stackable": true,
      "maxStack": 50,
      "description": "Raw chunks of hopeite-bearing rock.",
      "type": "resource",
      "value": 6
    },
    {
      "id": "hopeite_ingot",
      "name": "Hopeite Ingot",
      "color": "#c68a3a",
      "stackable": true,
      "maxStack": 50,
      "description": "A smelted bar of hopeite. Ready for the anvil.",
      "type": "resource",
      "value": 22
    },
    {
      "id": "hopeite_sword",
      "name": "Hopeite Sword",
      "color": "#c68a3a",
      "stackable": false,
      "maxStack": 1,
      "description": "Sharper than a plain iron blade. Forged at the anvil.",
      "type": "weapon",
      "slot": "mainHand",
      "stats": { "attack": 6 },
      "visualLayer": { "layer": "tool", "variant": "iron-sword" },
      "value": 180
    },
    {
      "id": "hopeite_pickaxe",
      "name": "Hopeite Pickaxe",
      "color": "#c68a3a",
      "stackable": false,
      "maxStack": 1,
      "description": "A hefty pickaxe tipped with hopeite.",
      "type": "tool",
      "slot": "mainHand",
      "skill": "orecheologist",
      "visualLayer": { "layer": "tool", "variant": "iron-pickaxe" },
      "value": 140
    },
    {
      "id": "hopeite_axe",
      "name": "Hopeite Axe",
      "color": "#c68a3a",
      "stackable": false,
      "maxStack": 1,
      "description": "A felling axe with a keen hopeite edge.",
      "type": "tool",
      "slot": "mainHand",
      "skill": "lumberjack",
      "visualLayer": { "layer": "tool", "variant": "iron-axe" },
      "value": 140
    },
    {
      "id": "smithing_hammer",
      "name": "Smithing Hammer",
      "color": "#9a6b3a",
      "stackable": false,
      "maxStack": 1,
      "description": "A cross-peen hammer. Lets you work the anvil more cleanly (future Blacksmith stat bonus).",
      "type": "tool",
      "skill": "blacksmith",
      "value": 35
    },
    {
      "id": "signet_ring",
      "name": "Captain's Signet",
      "color": "#e5c14a",
      "stackable": false,
      "maxStack": 1,
      "description": "Bronze ring bearing an unfamiliar crest. Feels lucky.",
      "type": "armor",
      "slot": "ring",
      "stats": { "sailSpeed": 6, "maxHp": 2 },
      "value": 500
    }
  ]
}
