{"chunkSize":32,"tileWidth":32,"tileHeight":32,"oceanGid":61,"tilesetSource":"tilesets/roguelike.tsx","startChunk":{"cx":1,"cy":0},"authoredChunks":["0_0","1_0","2_0","3_0","4_0","5_0","0_1","1_1","2_1","3_1","4_1","5_1","0_2","1_2","2_2","3_2","4_2","5_2","0_3","1_3","2_3","3_3","4_3","5_3","0_4","1_4","2_4","3_4","4_4","5_4","0_5","1_5","2_5","3_5","4_5","5_5"],"tilesetImages":["tilesets/Atlas-Props-sheet1.png","tilesets/Atlas-Props-sheet2.png","tilesets/Atlas-Props-sheet3.png","tilesets/Atlas-Props4-crops update.png","tilesets/Beach-transition tiles between coast platform and beach-spritesheet - Godot.png","tilesets/Beach-transition tiles between coast platform and beach-spritesheet.png","tilesets/Beach-transition tiles between coast platform and beach-spritesheet__Beach.png","tilesets/Free_Premade_houses.png","tilesets/Interiors_tilesets.png","tilesets/Premade_houses.png","tilesets/Premade_houses2.png","tilesets/Premade_houses3.png","tilesets/Tileset-Terrain-new grass - transparency.png","tilesets/Tileset-Terrain-new grass.png","tilesets/Update 1.2 - recolored roof.png","tilesets/animated Palm Tree-1-foliage-shadow.padded.png","tilesets/animated Palm Tree-1-foliage-shadow2.padded.png","tilesets/animated Palm Tree-1-foliage.padded.png","tilesets/animated Palm Tree-1.padded.png","tilesets/animated Palm Tree-2-foliage-shadow.padded.png","tilesets/animated Palm Tree-2-foliage-shadow2.png","tilesets/animated Palm Tree-2-foliage.padded.png","tilesets/animated Palm Tree-2.padded.png","tilesets/animated Palm Tree-3-foliage-shadow.padded.png","tilesets/animated Palm Tree-3-foliage.padded.png","tilesets/animated Palm Tree-3.padded.png","tilesets/banner-2-anim-neutral.png","tilesets/banner-2-anim.png","tilesets/banner-anim-neutral.png","tilesets/banner-anim.png","tilesets/banner-only.png","tilesets/beach - standard - no thick foam - spritesheet - Godot.png","tilesets/beach - standard - no thick foam - spritesheet.png","tilesets/beach - standard - with thick foam - spritesheet - Godot.png","tilesets/beach - standard - with thick foam - spritesheet.png","tilesets/beach - standard - with thick foam - spritesheet__Beach.png","tilesets/boat-idle-down.png","tilesets/boat-idle-sideways.png","tilesets/boat-idle-up.png","tilesets/boat-sailing-down.png","tilesets/boat-sailing-sideways.png","tilesets/boat-sailing-up.png","tilesets/buried chest-opening-gold.png","tilesets/buried chest-opening-half buried-gold.png","tilesets/buried chest-opening-half buried.png","tilesets/buried chest-opening.png","tilesets/decorations.png","tilesets/fence-curved.png","tilesets/fence-straight.png","tilesets/fertilized soil.png","tilesets/flag-pirate.png","tilesets/flag-pirate2.padded.png","tilesets/furniture_and_props.png","tilesets/gems-1.png","tilesets/gems-2.png","tilesets/gems-3.png","tilesets/gems-4.png","tilesets/hole- transparency.png","tilesets/hole-extra grass shade.png","tilesets/hole-main.png","tilesets/platform - grass(transparency) - coast - spritesheet.png","tilesets/platform - grass(transparency) - coast - spritesheet__Platform_-_grass_to_water.png","tilesets/platform - grass(transparency)- coast - spritesheet - Godot.png","tilesets/platform - grass2- coast - spritesheet - Godot.png","tilesets/platform - grass2- coast - spritesheet.png","tilesets/platform - grass2- coast - spritesheet__Platform_-_grass_to_water.png","tilesets/platform -grass(transparency) to water-spritesheet - Godot.png","tilesets/platform -grass(transparency) to water-spritesheet.png","tilesets/platform -grass2 to water-spritesheet - Godot.png","tilesets/platform -grass2 to water-spritesheet.png","tilesets/props.png","tilesets/props__tilesets_and_props.png","tilesets/roofs1.png","tilesets/roofs1_intersections_wall-width10.png","tilesets/roofs2.png","tilesets/roofs2_intersections_wall-width10.png","tilesets/sea-color variation-spritesheet.png","tilesets/ship-animations - down-idle-baked.png","tilesets/ship-animations - down-sailing-baked.png","tilesets/ship-animations - down-sailing-windFX.png","tilesets/ship-animations - up-idle-baked.png","tilesets/ship-animations - up-sailing-baked.png","tilesets/ship-animations - up-sailing-windFX.png","tilesets/ship-animations-sideways-idle-baked.png","tilesets/ship-animations-sideways-sailing-baked.png","tilesets/ship-animations-sideways-sailing-windFX-baked.png","tilesets/side_roofs_details_extrusion.png","tilesets/side_roofs_details_extrusion2.png","tilesets/tilesets.png","tilesets/tilesets__tilesets_and_props.png","tilesets/wall1 - transparency.png","tilesets/wall1-3tiles-transp.png","tilesets/wall1-3tiles.png","tilesets/wall1.png","tilesets/walls-floor1.png","tilesets/walls1.png","tilesets/walls2.png","tilesets/walls3.png","tilesets/walls4.png","tilesets/walls5.png","tilesets/water to grass(transparency) - river orientation-spritesheet - godot.png","tilesets/water to grass(transparency) - river orientation-spritesheet.png","tilesets/water to grass2 - river orientation-spritesheet - godot.png","tilesets/water to grass2 - river orientation-spritesheet.png","tilesets/wind fx-48frames.png"],"chunkTilesets":{"0_0":["tilesets/Beach-transition tiles between coast platform and beach-spritesheet.png","tilesets/beach - standard - with thick foam - spritesheet.png","tilesets/platform - grass(transparency) - coast - spritesheet.png","tilesets/platform - grass2- coast - spritesheet.png","tilesets/props.png","tilesets/sea-color variation-spritesheet.png","tilesets/ship-animations - down-idle-baked.png","tilesets/ship-animations - down-sailing-baked.png","tilesets/ship-animations - down-sailing-windFX.png","tilesets/ship-animations - up-idle-baked.png","tilesets/ship-animations - up-sailing-baked.png","tilesets/ship-animations - up-sailing-windFX.png","tilesets/ship-animations-sideways-idle-baked.png","tilesets/ship-animations-sideways-sailing-baked.png","tilesets/ship-animations-sideways-sailing-windFX-baked.png","tilesets/tilesets.png"],"1_0":["tilesets/Atlas-Props-sheet1.png","tilesets/Atlas-Props-sheet2.png","tilesets/Atlas-Props-sheet3.png","tilesets/Atlas-Props4-crops update.png","tilesets/Beach-transition tiles between coast platform and beach-spritesheet - Godot.png","tilesets/Beach-transition tiles between coast platform and beach-spritesheet__Beach.png","tilesets/Tileset-Terrain-new grass - transparency.png","tilesets/Tileset-Terrain-new grass.png","tilesets/beach - standard - no thick foam - spritesheet - Godot.png","tilesets/beach - standard - no thick foam - spritesheet.png","tilesets/beach - standard - with thick foam - spritesheet - Godot.png","tilesets/beach - standard - with thick foam - spritesheet.png","tilesets/beach - standard - with thick foam - spritesheet__Beach.png","tilesets/fence-curved.png","tilesets/fence-straight.png","tilesets/fertilized soil.png","tilesets/hole- transparency.png","tilesets/hole-extra grass shade.png","tilesets/hole-main.png","tilesets/platform - grass(transparency) - coast - spritesheet__Platform_-_grass_to_water.png","tilesets/platform - grass(transparency)- coast - spritesheet - Godot.png","tilesets/platform - grass2- coast - spritesheet - Godot.png","tilesets/platform - grass2- coast - spritesheet__Platform_-_grass_to_water.png","tilesets/platform -grass(transparency) to water-spritesheet - Godot.png","tilesets/platform -grass(transparency) to water-spritesheet.png","tilesets/platform -grass2 to water-spritesheet - Godot.png","tilesets/platform -grass2 to water-spritesheet.png","tilesets/props.png","tilesets/sea-color variation-spritesheet.png","tilesets/tilesets.png","tilesets/wall1 - transparency.png","tilesets/wall1-3tiles-transp.png","tilesets/wall1-3tiles.png","tilesets/wall1.png","tilesets/water to grass(transparency) - river orientation-spritesheet - godot.png","tilesets/water to grass(transparency) - river orientation-spritesheet.png","tilesets/water to grass2 - river orientation-spritesheet - godot.png","tilesets/water to grass2 - river orientation-spritesheet.png"],"2_0":["tilesets/beach - standard - with thick foam - spritesheet.png","tilesets/sea-color variation-spritesheet.png"],"3_0":["tilesets/sea-color variation-spritesheet.png"],"4_0":["tilesets/Beach-transition tiles between coast platform and beach-spritesheet.png","tilesets/beach - standard - with thick foam - spritesheet.png","tilesets/platform - grass(transparency) - coast - spritesheet.png","tilesets/platform - grass2- coast - spritesheet.png","tilesets/props.png","tilesets/sea-color variation-spritesheet.png","tilesets/tilesets.png"],"5_0":["tilesets/Beach-transition tiles between coast platform and beach-spritesheet.png","tilesets/beach - standard - with thick foam - spritesheet.png","tilesets/beach - standard - with thick foam - spritesheet__Beach.png","tilesets/platform - grass(transparency) - coast - spritesheet.png","tilesets/platform - grass2- coast - spritesheet.png","tilesets/props.png","tilesets/sea-color variation-spritesheet.png","tilesets/tilesets.png"],"0_1":["tilesets/sea-color variation-spritesheet.png"],"1_1":["tilesets/Atlas-Props-sheet2.png","tilesets/platform -grass2 to water-spritesheet - Godot.png","tilesets/props.png","tilesets/sea-color variation-spritesheet.png","tilesets/wall1 - transparency.png","tilesets/wall1.png"],"2_1":["tilesets/sea-color variation-spritesheet.png"],"3_1":["tilesets/sea-color variation-spritesheet.png"],"4_1":["tilesets/Beach-transition tiles between coast platform and beach-spritesheet.png","tilesets/beach - standard - with thick foam - spritesheet.png","tilesets/platform - grass(transparency) - coast - spritesheet.png","tilesets/platform - grass2- coast - spritesheet.png","tilesets/props.png","tilesets/sea-color variation-spritesheet.png","tilesets/tilesets.png"],"5_1":["tilesets/Beach-transition tiles between coast platform and beach-spritesheet.png","tilesets/beach - standard - with thick foam - spritesheet.png","tilesets/platform - grass(transparency) - coast - spritesheet.png","tilesets/platform - grass2- coast - spritesheet.png","tilesets/props.png","tilesets/sea-color variation-spritesheet.png","tilesets/tilesets.png"],"0_2":["tilesets/beach - standard - with thick foam - spritesheet.png","tilesets/sea-color variation-spritesheet.png"],"1_2":["tilesets/Atlas-Props-sheet1.png","tilesets/Atlas-Props-sheet2.png","tilesets/Beach-transition tiles between coast platform and beach-spritesheet.png","tilesets/Beach-transition tiles between coast platform and beach-spritesheet__Beach.png","tilesets/Free_Premade_houses.png","tilesets/Premade_houses.png","tilesets/Premade_houses2.png","tilesets/Premade_houses3.png","tilesets/Tileset-Terrain-new grass - transparency.png","tilesets/Tileset-Terrain-new grass.png","tilesets/Update 1.2 - recolored roof.png","tilesets/beach - standard - no thick foam - spritesheet - Godot.png","tilesets/beach - standard - no thick foam - spritesheet.png","tilesets/beach - standard - with thick foam - spritesheet - Godot.png","tilesets/beach - standard - with thick foam - spritesheet.png","tilesets/beach - standard - with thick foam - spritesheet__Beach.png","tilesets/decorations.png","tilesets/platform - grass(transparency) - coast - spritesheet.png","tilesets/platform - grass(transparency) - coast - spritesheet__Platform_-_grass_to_water.png","tilesets/platform - grass2- coast - spritesheet.png","tilesets/platform -grass2 to water-spritesheet - Godot.png","tilesets/props__tilesets_and_props.png","tilesets/roofs1.png","tilesets/roofs1_intersections_wall-width10.png","tilesets/roofs2.png","tilesets/roofs2_intersections_wall-width10.png","tilesets/sea-color variation-spritesheet.png","tilesets/side_roofs_details_extrusion.png","tilesets/side_roofs_details_extrusion2.png","tilesets/tilesets.png","tilesets/tilesets__tilesets_and_props.png","tilesets/walls-floor1.png","tilesets/walls1.png","tilesets/walls2.png","tilesets/walls3.png","tilesets/walls4.png","tilesets/walls5.png"],"2_2":["tilesets/Atlas-Props-sheet1.png","tilesets/Atlas-Props-sheet3.png","tilesets/Premade_houses2.png","tilesets/Premade_houses3.png","tilesets/Tileset-Terrain-new grass - transparency.png","tilesets/Tileset-Terrain-new grass.png","tilesets/beach - standard - with thick foam - spritesheet__Beach.png","tilesets/fence-straight.png","tilesets/fertilized soil.png","tilesets/sea-color variation-spritesheet.png","tilesets/water to grass(transparency) - river orientation-spritesheet.png"],"3_2":["tilesets/Tileset-Terrain-new grass.png","tilesets/beach - standard - with thick foam - spritesheet.png","tilesets/sea-color variation-spritesheet.png"],"4_2":["tilesets/Beach-transition tiles between coast platform and beach-spritesheet.png","tilesets/beach - standard - with thick foam - spritesheet.png","tilesets/platform - grass(transparency) - coast - spritesheet.png","tilesets/platform - grass2- coast - spritesheet.png","tilesets/props.png","tilesets/sea-color variation-spritesheet.png","tilesets/tilesets.png"],"5_2":["tilesets/Beach-transition tiles between coast platform and beach-spritesheet.png","tilesets/beach - standard - with thick foam - spritesheet.png","tilesets/platform - grass(transparency) - coast - spritesheet.png","tilesets/platform - grass2- coast - spritesheet.png","tilesets/props.png","tilesets/sea-color variation-spritesheet.png","tilesets/tilesets.png"],"0_3":["tilesets/sea-color variation-spritesheet.png"],"1_3":["tilesets/Atlas-Props-sheet1.png","tilesets/Atlas-Props-sheet2.png","tilesets/Beach-transition tiles between coast platform and beach-spritesheet.png","tilesets/Free_Premade_houses.png","tilesets/Premade_houses2.png","tilesets/Tileset-Terrain-new grass - transparency.png","tilesets/Tileset-Terrain-new grass.png","tilesets/beach - standard - with thick foam - spritesheet - Godot.png","tilesets/beach - standard - with thick foam - spritesheet.png","tilesets/platform - grass2- coast - spritesheet - Godot.png","tilesets/props__tilesets_and_props.png","tilesets/sea-color variation-spritesheet.png","tilesets/tilesets__tilesets_and_props.png"],"2_3":["tilesets/Atlas-Props-sheet3.png","tilesets/Free_Premade_houses.png","tilesets/Premade_houses.png","tilesets/Premade_houses2.png","tilesets/Premade_houses3.png","tilesets/Tileset-Terrain-new grass - transparency.png","tilesets/Tileset-Terrain-new grass.png","tilesets/roofs2.png","tilesets/sea-color variation-spritesheet.png","tilesets/side_roofs_details_extrusion2.png","tilesets/tilesets.png","tilesets/water to grass(transparency) - river orientation-spritesheet.png"],"3_3":["tilesets/Free_Premade_houses.png","tilesets/Premade_houses.png","tilesets/Tileset-Terrain-new grass.png","tilesets/roofs2.png","tilesets/sea-color variation-spritesheet.png"],"4_3":["tilesets/Beach-transition tiles between coast platform and beach-spritesheet.png","tilesets/beach - standard - with thick foam - spritesheet.png","tilesets/platform - grass(transparency) - coast - spritesheet.png","tilesets/platform - grass2- coast - spritesheet.png","tilesets/props.png","tilesets/sea-color variation-spritesheet.png","tilesets/tilesets.png"],"5_3":["tilesets/Beach-transition tiles between coast platform and beach-spritesheet.png","tilesets/beach - standard - with thick foam - spritesheet.png","tilesets/platform - grass(transparency) - coast - spritesheet.png","tilesets/platform - grass2- coast - spritesheet.png","tilesets/props.png","tilesets/sea-color variation-spritesheet.png","tilesets/tilesets.png"],"0_4":["tilesets/Beach-transition tiles between coast platform and beach-spritesheet.png","tilesets/beach - standard - with thick foam - spritesheet.png","tilesets/platform - grass(transparency) - coast - spritesheet.png","tilesets/platform - grass2- coast - spritesheet.png","tilesets/props.png","tilesets/sea-color variation-spritesheet.png","tilesets/tilesets.png"],"1_4":["tilesets/Beach-transition tiles between coast platform and beach-spritesheet.png","tilesets/beach - standard - with thick foam - spritesheet.png","tilesets/platform - grass(transparency) - coast - spritesheet.png","tilesets/platform - grass2- coast - spritesheet.png","tilesets/props.png","tilesets/sea-color variation-spritesheet.png","tilesets/tilesets.png"],"2_4":["tilesets/Beach-transition tiles between coast platform and beach-spritesheet.png","tilesets/beach - standard - with thick foam - spritesheet.png","tilesets/platform - grass(transparency) - coast - spritesheet.png","tilesets/platform - grass2- coast - spritesheet.png","tilesets/props.png","tilesets/sea-color variation-spritesheet.png","tilesets/tilesets.png"],"3_4":["tilesets/Beach-transition tiles between coast platform and beach-spritesheet.png","tilesets/beach - standard - with thick foam - spritesheet.png","tilesets/platform - grass(transparency) - coast - spritesheet.png","tilesets/platform - grass2- coast - spritesheet.png","tilesets/props.png","tilesets/sea-color variation-spritesheet.png","tilesets/tilesets.png"],"4_4":["tilesets/Beach-transition tiles between coast platform and beach-spritesheet.png","tilesets/beach - standard - with thick foam - spritesheet.png","tilesets/platform - grass(transparency) - coast - spritesheet.png","tilesets/platform - grass2- coast - spritesheet.png","tilesets/props.png","tilesets/sea-color variation-spritesheet.png","tilesets/tilesets.png"],"5_4":["tilesets/Beach-transition tiles between coast platform and beach-spritesheet.png","tilesets/beach - standard - with thick foam - spritesheet.png","tilesets/platform - grass(transparency) - coast - spritesheet.png","tilesets/platform - grass2- coast - spritesheet.png","tilesets/props.png","tilesets/sea-color variation-spritesheet.png","tilesets/tilesets.png"],"0_5":["tilesets/Beach-transition tiles between coast platform and beach-spritesheet.png","tilesets/beach - standard - with thick foam - spritesheet.png","tilesets/platform - grass(transparency) - coast - spritesheet.png","tilesets/platform - grass2- coast - spritesheet.png","tilesets/props.png","tilesets/sea-color variation-spritesheet.png","tilesets/tilesets.png"],"1_5":["tilesets/Beach-transition tiles between coast platform and beach-spritesheet.png","tilesets/beach - standard - with thick foam - spritesheet.png","tilesets/platform - grass(transparency) - coast - spritesheet.png","tilesets/platform - grass2- coast - spritesheet.png","tilesets/props.png","tilesets/sea-color variation-spritesheet.png","tilesets/tilesets.png"],"2_5":["tilesets/Beach-transition tiles between coast platform and beach-spritesheet.png","tilesets/beach - standard - with thick foam - spritesheet.png","tilesets/platform - grass(transparency) - coast - spritesheet.png","tilesets/platform - grass2- coast - spritesheet.png","tilesets/props.png","tilesets/sea-color variation-spritesheet.png","tilesets/tilesets.png"],"3_5":["tilesets/Beach-transition tiles between coast platform and beach-spritesheet.png","tilesets/beach - standard - with thick foam - spritesheet.png","tilesets/platform - grass(transparency) - coast - spritesheet.png","tilesets/platform - grass2- coast - spritesheet.png","tilesets/props.png","tilesets/sea-color variation-spritesheet.png","tilesets/tilesets.png"],"4_5":["tilesets/Beach-transition tiles between coast platform and beach-spritesheet.png","tilesets/beach - standard - with thick foam - spritesheet.png","tilesets/platform - grass(transparency) - coast - spritesheet.png","tilesets/platform - grass2- coast - spritesheet.png","tilesets/props.png","tilesets/sea-color variation-spritesheet.png","tilesets/tilesets.png"],"5_5":["tilesets/Beach-transition tiles between coast platform and beach-spritesheet.png","tilesets/beach - standard - with thick foam - spritesheet.png","tilesets/platform - grass(transparency) - coast - spritesheet.png","tilesets/platform - grass2- coast - spritesheet.png","tilesets/props.png","tilesets/sea-color variation-spritesheet.png","tilesets/tilesets.png"]},"chunkSpawnRefs":{"1_0":{"npcs":["brom_blacksmith","elin_innkeeper","garra_chef","jory_miner","lilan_florist","old_salt_fisherman","tomas_farmer"],"enemies":["slime_medium_red","slime_small_blue","slime_small_green"],"nodes":["fishing_spot","ore_hopeite","tree_palm"]},"1_2":{"npcs":[],"enemies":["skeleton","slime_small_green"],"nodes":["tree_palm"]},"2_2":{"npcs":[],"enemies":["skeleton","skeleton_swordsman"],"nodes":[]}},"interiors":{"cabin":{"path":"interiors/cabin.tmj"},"starter_dungeon":{"path":"interiors/starter_dungeon.tmj"}},"ships":{"galleon-e":{"path":"ships/galleon-e.tmj"},"galleon-n":{"path":"ships/galleon-n.tmj"},"galleon-s":{"path":"ships/galleon-s.tmj"},"galleon-w":{"path":"ships/galleon-w.tmj"},"rowboat-e":{"path":"ships/rowboat-e.tmj"},"rowboat-n":{"path":"ships/rowboat-n.tmj"},"rowboat-s":{"path":"ships/rowboat-s.tmj"},"rowboat-w":{"path":"ships/rowboat-w.tmj"}}}